{"wordsearch":{"term":"text","lemma":"text","startlocationpaper":"integer","endlocationpaper":"integer","sentencenum":"integer","articleid":"character varying","articleyear":"integer","articlecharcount":"integer"},"citation":{"id":"integer","citationid":"character varying","endlocationpaper":"integer","endlocationpara":"integer","startlocationpaper":"integer","startlocationpara":"integer","articleid_id":"character varying","citationmeta_id":"integer","paragraphid_id":"integer","sentence_id":"integer","reference_id":"integer"},"article":{"id":"character varying","articletitle":"character varying","articleyear":"integer","charcount":"integer","journaltitle":"character varying","papertext":"character varying","doi":"character varying","pmc":"character varying","authors":"character varying","fauthor":"character varying","filename":"character varying"},"sentence":{"id":"integer","endlocationpaper":"integer","endlocationpara":"integer","sentencenum":"integer","startlocationpaper":"integer","startlocationpara":"integer","para_id":"integer"},"citationmeta":{"id":"integer","articletitle":"character varying","authors":"character varying","citationnumpaper":"integer","year":"character varying"},"word":{"id":"integer","endlocationpaper":"integer","endlocationpara":"integer","lemma":"text","startlocationpaper":"integer","startlocationpara":"integer","term":"text","articleid_id":"character varying","paragraphid_id":"integer","sentence_id":"integer"},"paragraph":{"id":"integer","charcount":"integer","endlocationpaper":"integer","sentencecount":"integer","startlocationpaper":"integer","articleid_id":"character varying","sectionid_id":"integer"},"section":{"id":"integer","endlocationpaper":"integer","sectionid":"text","sectiontitle":"text","startlocationpaper":"integer","articleid_id":"character varying"},"citationsearch":{"startlocationpaper":"integer","endlocationpaper":"integer","sentencenum":"integer","articleid":"character varying","articleyear":"integer","citationauthors":"text","citationyear":"character varying","citationarticletitle":"text"},"temp_citationmeta":{"id":"integer","articletitle":"character varying","authors":"character varying","citationnumpaper":"integer","year":"character varying","articleid":"character varying"},"reference":{"id":"integer","pmid":"character varying","pmc":"character varying","doi":"character varying","raw":"character varying","articletitle":"character varying","articlesource":"character varying","fauthor":"character varying","authors":"character varying","articleyear":"integer","article_id":"character varying","referencetype":"character varying"},"temp_article":{"id":"character varying","articletitle":"character varying","articleyear":"integer","charcount":"integer","journaltitle":"character varying","papertext":"character varying","doi":"character varying","pmc":"character varying","authors":"character varying","fauthor":"character varying","filename":"character varying"},"temp_citation":{"id":"integer","citationid":"character varying","endlocationpaper":"integer","endlocationpara":"integer","startlocationpaper":"integer","startlocationpara":"integer","articleid_id":"character varying","citationmeta_id":"integer","paragraphid_id":"integer","sentence_id":"integer","reference_id":"integer"},"citation_ref":{"articleid":"character varying","citationid":"character varying","reference_id":"integer"},"signalcategory":{"id":"integer","catname":"character varying","score":"integer","enabled":"boolean","cookieid":"character varying","color":"character varying"},"whoosh":{"id":"character varying"},"signaltype":{"id":"integer","name":"character varying","type":"integer","psignalid":"integer"},"signal":{"id":"integer","signal":"character varying","score":"character varying","signalcategoryid":"integer","enabled":"boolean","cookieid":"character varying","signaltypeid":"integer","distance":"integer","parentid":"integer"},"querycache":{"queryid":"character varying","querydate":"timestamp without time zone","querydata":"character varying"}}